dpplgngr/__init__.py
dpplgngr/etl/__init__.py
dpplgngr/etl/convert_to_parquet.py
dpplgngr/etl/prep_dataset_tabular.py
dpplgngr/models/__init__.py
dpplgngr/models/graph_imputer.py
dpplgngr/models/vanilla_ae.py
dpplgngr/scores/__init__.py
dpplgngr/scores/audit.py
dpplgngr/scores/calculate_scores.py
dpplgngr/scores/cox_predict.py
dpplgngr/scores/evaluate_scores.py
dpplgngr/scores/maggic.py
dpplgngr/scores/privacy.py
dpplgngr/scores/pyMarker.py
dpplgngr/snowflake_config/__init__.py
dpplgngr/snowflake_config/amc_schema_etl.py
dpplgngr/snowflake_config/amc_schema_etl_sub.py
dpplgngr/train/__init__.py
dpplgngr/train/alternative_imputation.py
dpplgngr/train/graph_imputation.py
dpplgngr/train/lning.py
dpplgngr/train/sdv.py
dpplgngr/utils/__init__.py
dpplgngr/utils/definitions.py
dpplgngr/utils/functions.py
dpplgngr/utils/luigi_replacement.py
dpplgngr/utils/score_config_utils.py
dpplgngr/utils/study_config.py
dpplgngr/utils/utils_data.py
dpplgngr/utils/utils_etl.py
dpplgngr/utils/utils_train.py
dpplgngr-0.4.0.dist-info/licenses/LICENSE
dpplgngr-0.4.0.dist-info/METADATA
dpplgngr-0.4.0.dist-info/WHEEL
dpplgngr-0.4.0.dist-info/top_level.txt
dpplgngr-0.4.0.dist-info/RECORD
