Metadata-Version: 2.4
Name: dpplgngr
Version: 0.4.0
Summary: Deep-learning automated twinning
Home-page: https://github.com/tevien/Doppelganger
Author: Sean Benson
Author-email: s.h.benson@amsterdamumc.nl
License: MIT
Classifier: Development Status :: 3 - Alpha
Classifier: Intended Audience :: Developers
Classifier: License :: OSI Approved :: MIT License
Classifier: Programming Language :: Python :: 3
Requires-Python: >=3.9
License-File: LICENSE
Dynamic: author
Dynamic: author-email
Dynamic: classifier
Dynamic: home-page
Dynamic: license
Dynamic: license-file
Dynamic: requires-python
Dynamic: summary
